qtom/__init__.py
qtom/cli/__init__.py
qtom/cli/evaluate.py
qtom/cli/generate_data.py
qtom/cli/train.py
qtom/core/__init__.py
qtom/core/data_generation.py
qtom/core/povm.py
qtom/core/random_states.py
qtom/core/state_representation.py
qtom/evaluation/__init__.py
qtom/evaluation/metrics.py
qtom/models/__init__.py
qtom/models/neural_network.py
qtom/models/training.py
qtom/utils/__init__.py
qtom/utils/io.py
qtom-1.0.2.dist-info/licenses/LICENSE
qtom-1.0.2.dist-info/METADATA
qtom-1.0.2.dist-info/WHEEL
qtom-1.0.2.dist-info/entry_points.txt
qtom-1.0.2.dist-info/top_level.txt
qtom-1.0.2.dist-info/RECORD
