Metadata-Version: 2.4
Name: qtom
Version: 1.0.2
Summary: Neural Network Quantum State Tomography Library
Home-page: https://github.com/alhazacod/qtom
Author: Manuel A. Garcia & Johan Garzon
Author-email: mangarciama@unal.edu.co
Project-URL: Bug Reports, https://github.com/alhazacod/qtom/issues
Project-URL: Source, https://github.com/alhazacod/qtom
Keywords: quantum,tomography,neural networks,machine learning
Classifier: Development Status :: 4 - Beta
Classifier: Intended Audience :: Science/Research
Classifier: License :: OSI Approved :: GNU General Public License v3 (GPLv3)
Classifier: Operating System :: OS Independent
Classifier: Programming Language :: Python :: 3
Classifier: Programming Language :: Python :: 3.7
Classifier: Programming Language :: Python :: 3.8
Classifier: Programming Language :: Python :: 3.9
Classifier: Programming Language :: Python :: 3.10
Classifier: Topic :: Scientific/Engineering
Classifier: Topic :: Scientific/Engineering :: Physics
Classifier: Topic :: Scientific/Engineering :: Artificial Intelligence
Requires-Python: >=3.7
License-File: LICENSE
Requires-Dist: numpy>=1.19.0
Requires-Dist: tensorflow>=2.5.0
Requires-Dist: keras>=2.5.0
Dynamic: author
Dynamic: author-email
Dynamic: classifier
Dynamic: description
Dynamic: description-content-type
Dynamic: home-page
Dynamic: keywords
Dynamic: license-file
Dynamic: project-url
Dynamic: requires-dist
Dynamic: requires-python
Dynamic: summary
